controlgraph.py
controlgraph-0.7.1.dist-info/entry_points.txt
controlgraph-0.7.1.dist-info/LICENSE
controlgraph-0.7.1.dist-info/WHEEL
controlgraph-0.7.1.dist-info/METADATA
controlgraph-0.7.1.dist-info/RECORD
