Metadata-Version: 2.1
Name: controlgraph
Version: 0.7.1
Summary: Generate build order graph from directory of debian packaging repositories
Home-page: https://openswitch.net
License: UNKNOWN
Author: Dell inc.
Author-email: opx-infra@openswitch.net
Requires-Python: >=3.5,<4
Classifier: License :: OSI Approved :: MIT License
Requires-Dist: networkx
Requires-Dist: pydot
Requires-Dist: python-debian
Provides-Extra: .none
